info_file/__init__.py
info_file/info_file.py
info_file-1.0.dist-info/METADATA
info_file-1.0.dist-info/WHEEL
info_file-1.0.dist-info/top_level.txt
info_file-1.0.dist-info/RECORD
