Metadata-Version: 2.2
Name: info_file
Version: 1.0
Summary: The Official Interpreter for Info File.
Dynamic: summary
